{
  "governance-msg-a": "Ver proposta",
  "governance-msg-b": "por:",
  "governance-msg-c": "Título da proposta",
  "governance-msg-d": "Descrição da proposta",
  "governance-msg-e": "Mensagens executáveis",
  "governance-msg-f": "Informações Adicionais",
  "governance-msg-g": "Por favor, esteja ciente de que novas propostas podem levar alguns minutos para aparecerem no painel.",
  "governance-msg-h": "Quórum",
  "governance-msg-i": "Votos a favor",
  "governance-msg-j": "Votos contra",
  "governance-msg-k": "Na carteira:",
  "governance-msg-l": "XASTRO insuficiente para bloquear",
  "governance-msg-m": "Você não tem xASTRO suficiente em sua carteira para enviar uma proposta",
  "governance-msg-n": "Estacar Astro",
  "governance-msg-o": "copiar",
  "governance-msg-p": "Meu poder de voto",
  "governance-msg-q": "Vote a favor da",
  "governance-msg-r": "Vote contra",
  "governance-msg-s": "a favor da proposta",
  "governance-msg-t": "contra a proposta",
  "governance-msg-u": "Você não votou",
  "governance-msg-v": "Votos",
  "governance-msg-w": "Endereços",
  "governance-msg-x": "Fechar",
  "governance-msg-y": "Ver endereços",
  "governance-msg-z": "Enviar LUNA contida no contrato de Assembléia para outro endereço",
  "governance-msg-aa": "Defina o endereço_taxa no contrato de fábrica de bombay para terra...",
  "governance-msg-ab": "Defina o endereço_gerador no contrato de fábrica de bombay para terra...",
  "governance-msg-ac": "ativo",
  "governance-msg-ad": "sucesso",
  "governance-msg-ae": "falhou",
  "governance-msg-af": "expirado",
  "governance-msg-ag": "executado",
  "governance-msg-ah": "Propostas da Assembleia",
  "governance-msg-ai": "Enviar proposta",
  "governance-msg-aj": "Total de ASTRO Estacados",
  "governance-msg-ak": "APY",
  "governance-msg-al": "Proporção Estacada do Protocolo",
  "governance-msg-am": "Meu ASTRO",
  "governance-msg-an": "Estaque ASTRO por xASTRO para receber uma % da receita do Astroport.",
  "governance-msg-ao": "Para saber mais sobre Astroport, junte-se à nossa comunidade no Discord.",
  "governance-msg-ap": "Entrar no Discord",
  "governance-msg-aq": "ASTRO na minha carteira",
  "governance-msg-ar": "Meu saldo xASTRO",
  "governance-msg-as": "Desbloquear xASTRO",
  "governance-msg-at": "Página {{pageNum}} de {{pageCount}}",
  "governance-msg-au": "Ir para",
  "governance-msg-av": "Histórico da proposta",
  "governance-msg-aw": "Descrição",
  "governance-msg-ax": "Tem alguma opinião sobre esta proposta?",
  "governance-msg-ay": "Discuta com outras pessoas no fórum.",
  "governance-msg-az": "Ir para o Fórum",
  "governance-msg-ba": "Definir título:",
  "governance-msg-bb": "Inserir Descrição:",
  "governance-msg-bc": "Mensagens executáveis:",
  "governance-msg-bd": "Inserir link para discussão:",
  "governance-msg-be": "xASTRO atual",
  "governance-msg-bf": "Novo xASTRO",
  "governance-msg-bg": "Estaque ASTRO para receber xASTRO.",
  "governance-msg-bh": "Remova xASTRO para receber ASTRO.",
  "governance-msg-bi": "APY de xASTRO",
  "governance-msg-bj": "% de poder de voto",
  "governance-msg-bk": "Título da proposta",
  "governance-msg-bl": "Seu voto",
  "governance-msg-bm": "O período de votação terminou.",
  "governance-msg-bn": "para esta proposta",
  "governance-msg-bo": "contra esta proposta",
  "governance-msg-bp": "Você não pode votar em sua própria proposta.",
  "governance-msg-bq": "Confirmar Votação"
}
